{
"pojp3hsabrwdatphyp23egxy":["1nonlyzaz","💙 Zaz 💙"],
"g2hadwfsctqlqim5m4p6w2op":["ammyschl","Zaza"],
"fngfzmu7xwxxjvaec3njosq4":["amazeke","Zaz"],
"hl7gmwwebaxnjktekxi6v5kn":["azazelthevampire","Zazel"],
"6ttpgemwhh3rfvcedmoczohe":["brustring-z","Brustring Zazenhausen"],
"hpycjxkboedxh4h7hsbfcb6l":["busterknight","Zazmiel , Tiger Of Lust "],
"cn667iz7qroebcbqlx434l32":["catvapes","🩵 zazz 😈"],
"y7zp7xo3wzgj5jngnyt7lipr":["cadencezazerwit","Cadence Zazerwit"],
"j3no5fmaxhude24epmucno2b":["camozazlie","CamoZazlie"],
"crtqxyqgmmonzrg7g5gvugb4":["catzazou","Zazou & Lucy"],
"3pf6j5xjexvyv2ah3q26rpt2":["damezaza","Dame Zaza"],
"6gybabvtjbvmhkdf3rzun6g2":["depechechode","top shelf zaza disrupted my circadian rhythm "],
"3lbusersteil3au5o5mi3ukk":["elysivm","zaza :)"],
"eal6dljamgmh4ruogzn3edlx":["fagalloch","𝘢zazelˍ✰"],
"isno6iekgasbvczyf3eqjp2b":["ilocine","Zaza (aka ilocine)"],
"vif3e6ftavxnvi5vbonqb37m":["justzaz",". zaz ."],
"dbfrzsbrv5mud7fttsap3evs":["kristenzaza","Kristen Zaza"],
"rdk32oyeuhehr2sm2s3y7adb":["luzazu","Lucas Zazu"],
"bgn4l5ccjbtozaj27lrogesl":["lukezaz","LukeZaz"],
"vepmdnbyf5xyfiaorzoixagd":["madzazzy","Mad Zazzy"],
"xrsccym3xz7sccd45yi5ifoy":["maxzazharski","max zazharski"],
"gcvnkq5rjd3pfydj2agzn5tk":["mbembeart","Anthony 'Mbembe\" Zaza"],
"s3k2cs32td5vrqzc5etwmgjq":["mrbrodie","zaza"],
"olwck5tx4uny6vrvur7tzev3":["muchomaas","zaza gabor"],
"davoulkggi4ylhapabuvppzp":["mysteriousmsf","Alex/Zazz"],
"o37eobneflfpxourc7lwxi6y":["nanazazu","Natty / nana_zazou"],
"tl5ujzs46r2jnxlgmap6pf4z":["nickizaziki","NickiZaziki"],
"cjnoardwek3dub5gvzcvawfp":["notthatzazu","Zazu"],
"gtt2bmqwwzlexqofm6jgg3e4":["pixiezaz","Zaz"],
"n2dacbvc5qqcdapk7txdcs56":["proddi","Marcel Reis-Zaziki"],
"oplcohcls5uqruhfo3mhdhlb":["pupzazu","Pup Zazu - ehemals Mellow"],
"q7rfe653gazce36qhr2bakt4":["rembha","Zazu"],
"nxjtuslv3uvj6uym7ysu6cfa":["summerlawnsss","Matt Zazzarino"],
"ofavznl6pllaqcft5rgitspw":["sudosauz","Zuzzy zazz"],
"d62kb2cydynccvdgo7ktcpqp":["sunflowersaint","#1 Zazie Enthusiast "],
"hzidddjvsnr6mkxdj7pwzveg":["sweetzazu","SweetZazu"],
"wbp7y5pbxxsruf2nshtrvzpi":["thezazzypup","The Good Pup, Zazzy"],
"nijndtikxg5jv6rii3wjbhdi":["trashferret","Zazil"],
"sitf3ifd2szdrs2oitw7zaz2":["wiskrph","The Zaza Wizard"],
"ybz7eidhcsxv4try5r2l4lv3":["yak-zazvychay","Котёнок заебався"],
"doj5tw3ryzbfpbpw6uydhd5h":["z40zzaz","Zaz"],
"4br5fmdnqpoh3zrdbzwwdbhz":["zazasmoka","jimmy cocoapuff"],
"5vnm4x5dd246fgksfce57akb":["zazzles","standard pumpkin spice possum"],
"cfk7himm76zlmlbyqprzg6eh":["zazu","Daniel"],
"ckfrvxqjax32vgohwxkg3wln":["zazerdly","🎃Rosa🎃"],
"ddxhvryqf4dxxwqjyfpr5a22":["zazzyv","Zazzy Vageen"],
"drg7pfstejpg5nlodedbz7su":"zazafl",
"hesykkm6lk5ex3qohgyptibp":["zazengirl","kana"],
"idlottu45lhd2flnyvixnedg":["zaziel","Zaziel The Archangel "],
"u5j36gx7o46uydqbticxzlda":["zazouji","climate anxiety haver"],
"vmkhu6vhrz6wp6lvvjts6nv2":["zaza0642ukr","харківська булочка"],
"w632ctphr3h2xkbu73rb7qnq":["zazryo","zaz ✨"],
"ytxjy47ckblevp4gnzm6fs6w":["zazb","Guillaume Bonnet"],
"w2nfjx42nq7fm6yxt325n5tq":["zazathehutt","Comrade Rae Jepsen"],
"oxdd7fv63zd4qs6bhwxfli6c":["zaz","francesco strazzari"],
"lyxmjyhe2oizpyct2k3trdon":"zaza",
"kphyh3py7d2vtpaksksxdul7":"zaza110",
"2ismdpll7ze37qerps3bhd5w":["zazadawg","Zazadawg"],
"g3lhwdsi3zv5h3cffx7ishlr":"zaznoobot",
"y7kb2zb7tlwv5phwc65sgt5t":["zazasupersoldier","ZAZASUPERSOLDIER"],
"e4gqizwjzrqrdhq6vfgw2whq":["zahara","zaza"],
"x5cucxpig7ao4gxmkvf2y4nw":["zazietodd","Zazie Todd PhD"],
"6lucqxsnhhs7wbt7p3ywu4c6":["zazihardid","핑쿠"],
"b5kgrv5spdxwnmqjlu4h2dae":["zanato","zazazanato ⭐"],
"irw5vogoxpbfggubushpwwin":["zazrit","Zazrit"],
"j5ok34qcuwsxj7jiseoke4fy":"zazko",
"c22szt53ebm6tyd7san4qck2":"zazesspur",
"b7wokvohwvpzfidiv6fnpxqw":["zazoza","Dawson’s Creek"],
"xhc46epc34c4j77oyn67utfp":["zazc","zaza"],
"iztgurj3zihll4idxb2gsash":["zaziky","Zaziky"],
"x3rqjumyj6wjyhtbjcjfekgc":["zazz","Zazz"],
"lzoxhdf35lut26b4dfqzhsqb":"zazan",
"xkiiv32l5zjhuzjzr6sznrfu":["zazzy","Zazzy"],
"xhl2nhfu44xz66e7dgotjt54":["zazozu","zazozu"],
"gql6nvgof6ninr45v2ylwcvm":["zazzialwrite","Zazzi Alwrite"],
"xhbi5bgxdotvo2az6jhszb26":"zazearazcigiger",
"x6pkcxty4f7i5dnp6h24uykx":["zazie","Zazie"],
"nf6jfazk2qjvcvibxycofkbb":["zazistrangelove","Zazi, Drool Sovereign"],
"fpgfsoxt6zpit5wlhwayn3ph":["zaku709","Zazaa 🌸 an ube popoto"],
"hu5aqey75wob6zo7tobu3f2n":["zazashiva","Zakashiva"],
"srshj7mbe6lucspuzl3rixzo":"zazufrost",
"s72dsq43v47behagksrfoxig":"zazen280",
"6ljhjr6tpmeno5ctyxgfskl7":"zazadls",
"ndq5ocj5itmy4hn4avqotzxp":"zazoga",
"72kzv6ehen7yekfststwwuii":["zazareee","Saltimbanco"],
"k6rz5oisetdm4i4b7grvd3bu":"zazazarah",
"fwqfnlpx2jeyg7nzilbqyubn":["zazachk","zachk"],
"cbolwqwghhlosywvps7dvskl":"zazbrown",
"y2hflydispihgkao4f7yscxi":["zazelposs","Zazel Poss"],
"rro6efmzoa6n2vai5mrfttlh":["zazzlesthe7th","Zazz"],
"swc7jm2dw4v7ppzpru2bmgyf":["zazazenith","ZEN"],
"rlvozqx3lrnrveion7qpf7fd":"zazzie",
"gihw45ixm5wfx5afgnvftnc2":"zazagoblin",
"ikt5wzkqogui6gwgphx3fsnj":["zazaque7","Za"],
"aglu2t7bej4idjvurhjkspc3":["zaziss","Zaziss"],
"tbbf54ixdsxobt2awrc2f5ca":["zazzeaux","Sandy Parsons"],
"psiyhr6hof3fvipi3gee5b4x":["zazietokyo","Megu M"],
"wt3pvj2eqv7nkseohtgtupzk":["zazo","Stan Halen"],
"pqt3r4auxczoynreyelwv3ph":"zazi",
"pipzuwlhmf3zqwb6padlpguy":["zazazz","먹고자고"],
"hsqtjewwpa6uupu4fatc7h3k":["zazel","zazel"],
"ijc6dgvyx7h2jdzk4teqouqe":["zazelss","Zazelss🔜MFF"],
"o6pm6uyalrol6prhpe5mdd72":["zazehu","Bebouu"],
"6zhi6vnggq5lnrlw6tr5pjdp":["zazadapulos","Zazadapulos"],
"lrjt2ccpt7cmtouwqrueu24p":"zazztastic",
"c7zod7lpmkt5ugu4kxag54gb":["zazapicouze","Zazaploute"],
"znpf5ybr2hekvsd3sgkzep6k":["zazzao","Zazzao"],
"npva3jqa5lfjyb4ujysenrvx":["zazadpfs","нтпрмнг"],
"hfypix2l3micg46r23o6qvr7":["zazapachuliya","Zaza Pachulia"],
"m56jwwo7z23vs4gy6jn5xloj":["zazpihuts","エクス（zazpihuts）"],
"sw4uvvi2dbtflec3wl5rimsy":["zazgeek","ZazGeek"],
"pwrki2rfaudif3hjltnnlto4":["zazaza","baz"],
"dnuw3t26otup65xpgprb7uto":"zaznobatarakan",
"pjsibx3eqo2azkkp5g5ylzmc":["zazaa","Elisabeth"],
"csc3lgen3yoif73utzetvm4h":["zazelpire","🍷🦇Zaz🦇🍷"],
"ubts3vdhe4gyfpegfceouicg":"zaznaro",
"iwaf6q7wvcxzd2pyli3czor5":["zazzy1","Zazzy"],
"ataqv2kco3t7k25plflj6cmq":["zazelad","Dirty zazel "],
"i5tp4xq7esaw4rboiylshzxz":["zaziedanslemetro","Zazie "],
"aebwtzihrjemdut5dpsvj6ds":["zazelkobold","Zaz at the STᐰRGATE 🏳️‍🌈"],
"3vd2siavlafrkvpvkewpvfme":["za2a","Zaza"],
"yhcslskbst444faep4um4owl":"zazuki13",
"puwaln2wyjmguawa3qxaxpz3":["zazzycatisback","Zazzy Cat"],
"jhoojbbpxs7kkcfbtnnoc63d":["zazacorn","zaza corn"],
"dgp4bmb3oshci5haifnfbhm6":["zazrichor","zaz 🕸"],
"gvsolnlo6nwsolryh5vgqgtk":"zazou",
"xy2k3ceqngbyo5x6fvgfld6i":["zazuthe","Zazu MagPot"],
"gjt5r7njqk5h2u2g4qffgs4y":["zazounette","Isa Zazou ☀️🌺🌸"],
"pn3m4ynr5qwr3iclbaar2wzv":"zazuki1",
"r3bakfkzlg5dcjpuw5doyidt":["zazalenounours","Ange"],
"qkn5pzp6sh637t5hlgc3hauz":"zaz1k",
"lcdqtikyu6jekbaemga3qk4s":["zamadotx","Zaza Garcia"],
"mjbpmepmbl5foqb7zopuf5lp":["zazs","Zazs"],
"nmxr53k4nn32umwmphko6mf4":["zazzydoesstuff","ZazzyDoesStuff"],
"d4vq3uto4yc7mlxitaqtdvjt":["zazazeke","Himbo Hauler"],
"cbpyc5tyxpx7svljlyrgdhyw":"zazuki3",
"5a77c7bgs2ag2jfclihrsbu6":"zazufrost6",
"pybbjjeykmv2irekm2ur5opf":"zazzille",
"biguplk4vemtewzlafjjumy5":"zaziwal",
"gj5ihgcodardyg7tagcmbgqs":["zazy","Zazie"],
"nxo6hvpooernp3t6cz7oaekf":"zazaberg",
"sncsh7cu2jgiqep2ca6inglv":["zazz112","Zazz"],
"futvqvjb5iup632elv5igidq":["zazzzouu","Zazzzouu"],
"pvdwq5uvpbxkxf75l23aodhc":["zaz007","Zaz"],
"7gmwtggvvttqcbv7ojeyin46":["zazoo","Zazoo"],
"fydy7ihcrnk6cyj3g73pw77o":["zazalex","妖怪"],
"najy64xizbndkalkbhrjpcrj":"zazzed",
"rggwaohqwiveinzxnp444zfk":["zanzeoo","Zaza"],
"orswdrwyzcvrbv6r3erbokbj":"zaziemo",
"f6s7t2pbnc5q7ijdi72qzicn":"zazikel",
"rurhmkplgqqxdfgacqo6ztlg":["zaza0818","자자"],
"htsnuqhqcgotinivrsakolgu":"zazah",
"afej4jfrxh4w4yfeoq4jkpvv":["zazersi","Mia ♡"],
"kdfozo77c37yghnb46p4pl4a":"zazahuang",
"xf5skhzsivn5vy46dunzmmfs":["zazivt","ZaziVT"],
"jkewbyx74vm4zlwvlzwqd7lr":["zazadelille59","@Jabberwocky "],
"ytjmj7ti2iiuac3l4xcqlsfq":["zazzro","zazzro"],
"trfvenchsea2ko5ci66sb5hx":["zazazeem","ZaZaZeem"],
"sluuzerlavonwgrmzcoru5ms":["zazaki","Zaza"],
"rmopbq6jrai3utgj66ky5z5m":["zigzagzazz","Zazz!!!➡️Home(COMMS OPEN 0/2)"],
"ydbir6pc6v2c7hhmfp42ddlc":["zzzazzyzz","Zazzy (VTUBER!)"]
}
