{
"ydrxr676jtrwiflcnab3b7rh":["adorafolf","Zephyr 🦊🐺"],
"fhxvvi7dp5hmsat2h5kruc43":["alejandrozepeda","Alejandro Zepeda"],
"u6iavfmnmiby3jyr24qkvhpv":["alexiconarts","Alexicon, Zephyr Mage 🏳️‍⚧️🏳️‍🌈"],
"peemn5txckvp736zmpp35yyo":["amerikanakia","zeps"],
"gox5yeikmxq7rrfnfqlqd6k4":["angewomon","Zeph"],
"rrtjujjh6nvnisitqs2t7xcf":["anyazep","Anya Zeppeli 🧵ENCARGOS ABIERTOS🧵"],
"iqrmo3rllk2rptydrgl4osj3":["astarothewe","🧿🍀Zephyr🍀🧿"],
"sxv3fpkp2cvfpofukeuiv5gy":["athenzephyr","Athen zephyr"],
"xfe6n3ynjuzmdp3twbykqpzw":["aurozephyr","AuroZephyr"],
"4smmmgpfnxi6f2qipsnzvoq4":["auzeph","Au Zeph"],
"buoggcangcmbgcfnjq4hsnnc":["avizephyra","Avi Zephyra"],
"qgmmrgjznq42wsjwmswjizn3":["axiomtempest","Zephyr of the Stars"],
"d2x6gyg77nhecx7ruhdxus4a":["bathroombritches","Zephyrlot but hornier"],
"id2xxnalbnrptgydlotqnkls":["basementcritterzz","Zephyrus "],
"nytnia4fvecypbhd53xr23ku":["badbitchzephyr","Zephyr"],
"rayczld6gz5jvjoq37ryddes":["bimawen","Zeph"],
"fqxpkw6oz36dicm35agburcr":["bigzephyrwolfe","Zephyr Wolfe"],
"q2n4so4u2tqcinsvn4e36za6":["bluesabercat","Zephora BlueSaberCat"],
"yyknhxepak4bj2odz3esepv2":["bleakflower","Zephyr "],
"3lruyicluuyzouual4azdk3s":["caffeinatedzeph","🔞⚡Zeph⚡"],
"noao4wvwrcsgwqabbrrxydym":["chasecondon","ZephyrDawn"],
"bya3c57icwjyg747lfuhlp4r":["cognitivedissonant","zephyr f. sosin"],
"ssknbu64k4q7cjrtnbehcfwq":["coffeebunxiv","Zeph the Coffeebun"],
"3j6ygihuufoaxtpt65yp45gb":["cryomancerzeph","Zephyr 🏳️‍🌈"],
"sgpyxlr2itz5oti42wy5vwkx":["czpuede","Cristina Zepeda"],
"ttmijnnqynzv4hodftzqbdc3":["dapwrites","Zephyr"],
"xsdhkp2yf74qwauxgonmkihe":["davezeppelin","Dave Zeppelin"],
"5msccpmxkckxkfyw6o7v52h3":["deszeppelin","🔴DesZeppelin ⏮⏯⏭⏹⏏️"],
"v3v7leupluomcjqjb5p6el7a":["defectedzephyr","Defected Zephyr"],
"hmi2ajd5fy7a25taphiqmmof":["depsilorzepp","Depsilor Zepp 🦇"],
"zmezqqukrlxzqrttchotrgcs":["deadzeppdeath","Zeppu"],
"2hznuibpkdzksdjxlsd2ofvv":["dinozeppelin","DinoZeppelin"],
"ypwzxphp2vrumidtfscckz6l":["dogemperor","dogemperor (PLAY NEO:TWEWY, ZEPTOGRAMS)"],
"gyqh7yecofotb3j2yhrpscsf":["donaldz","Donald Zepeda"],
"rql2ih6vxg23nqxv4i2ixvmq":["dressfolklore","zeph"],
"tuvalwb6hzcnlw5pixqgcuny":["drmelz","Dr Melanie Zeppel"],
"gda3newlltoebgkmbkke6yk5":"elin-zepp",
"766p3xgtar2klie72mjkfvx4":["ensouledsteel","Zephyr"],
"zmo7jbpxy5nw5htrgahsrco6":["ereleiazephyria","Ereleia Zephyria"],
"btwmg6j6l5i6xsrl5xi3xzds":["eryaszephyrhog","Eryas Zephyrhog || VTUBER "],
"mjx2223qic6mippnphradmag":["fatassgiratina","Zephyr"],
"ncgrnk6eudvc4ltdqfc3gtzp":["fezandipiti","Hungry Zephyr~♡"],
"kh76knggv2kbyc5f6dclsmyw":["feralmiki","Miki Zephyrus(6.5 Arc)"],
"ikizpa5epbtx36ul6fubfbrj":["felisfuscus","Zephyr"],
"jht4t7oxih6vi45mg3aizdwx":["findingmeemos","zeph⚡️"],
"n6jicijjwnrhkmmkbdv6ri6l":["fluffderg.ch","Zephyr"],
"e4zehhxlgqe4aiilaxa6n63a":["flzroche","Roche Flunit-La Zepam"],
"rqrul6fkfgosh4dr2umr2cmc":["furryart","Zephyr "],
"box7v47ywdov2mkktynbvotk":["gm-zeppelin","GM Zeppelin"],
"znkntqsefd7slgsbqhkeln66":["gonetopluto","Charlie/Zephyr"],
"gacify7jtigszpc7pxctyjb2":["graysonsgremlin","YA BOI ZEPH "],
"sxi6h47iqr6xjw6ehoafglx2":["guybrushcreepwood","Zeph"],
"mm4gvuwqdzkp2s3batl5mvad":["guccigarf","🔥 Zep 🔥"],
"sqekhukjkcuapaeev46ghg4k":["halcyonzephyr","Zephyr"],
"c4cgzriui4fmwsec7ei3zisz":["heliaentheus","zephyr"],
"ydgqzg5w3emxngpt76qfh42t":["heckatiel","Zephyr Heck"],
"yxtiujwmcoz7tfylfitznkgm":["heliautem","🔞zephyr🔞"],
"ah7uc67gu5gmqwltjenjs4k7":["hexgirl","Zephyra"],
"gnawbjwn75tw6rba3l2ijc5l":["heartattackmp3","zeph' ✨"],
"37n5rsj436edi2yqjx5nlumv":["honorablezephyr","Zephyr The Paladin 🛡️"],
"ibg4orov63w7uu2xrleh5wh5":["hunterlzepeda","Hunter Zepeda"],
"7imv3omdcxfqp3rhsbzqapah":["hx-yy-z","Harrison Yu-Zepeda"],
"zgobndtupsdsumgcxzyx5xru":["hyoryusha","Zep"],
"vug2wefz6twvinym3xwgfatl":["ichaurem","Zeph"],
"h56sxrzy442nqaw46wzdd2fr":["imperishablenight","Zepolete"],
"dghwrjna7szrxbvgxjc4dfmg":["insalius","Insalius Zephyr"],
"b3vzh2xmuixy2lvmbdce2on3":["insxsni","Zephy🔞"],
"wc2uc62bacydiqag7sjcmm7l":["ipaleebo","Zephyr 🌹"],
"l2qvbzeugl3eh5uq5vefibxh":["itszephyr","Zephyr"],
"pgakufdmgkgtc2hytupxie6y":["jasminezephyr","Jasmine Zephyr"],
"2xbrgof4q6fwk2gm5nebdd5d":["januszephyrine","Janus Zephyrine"],
"2mxysghfdxkvwjjbxivni2mv":["jasonzephr","Jason Zephr Werewolf Himbo guy"],
"obrzfvhbznu3zgpllr44y6vu":["joe79","Joe/Zeph"],
"ic7henylzngc7vw47lffyvbg":["jokesterzephyr","Zephyr"],
"e4hhfvzksns3c6nmyvhojwyw":["justinzepperi","Justin Zepperi"],
"x5ywvevjfnfexsdihwwqnlg6":["l1ttleh3ll","Zephy 🖤 "],
"m2evwxdc7cevg4wtioeswkem":["ledzeppelin","Led Zeppelin"],
"726vyxniivaby75ew7m45ll6":["lexaloffle","zep.p8"],
"bf24hc3j4si5tisvxe3b7fpe":["littleredphantom","Zephyr!"],
"nzlks7ivrzmzvpmsfzdpcats":["lucerile","zeph⋆⁎✩"],
"hvoatom3hwzbvznxjf3bppkp":["luka.zephyr.pet","Luka"],
"oh3trwvjfum73e5klu57uq7e":["macawfeathers","Zephyr the Macaw 🦜"],
"tul6u3levcaiguqy6ngvtqgo":["mamazephis","🔞💚🔪🦊🐺🚬Mama_Zephis🚬🐺🦊🔪💚🔞"],
"6hmcxah7sdk3irsxyt4gzjg3":["maybenamedzeph","Zephyr Valgale"],
"ileqc6r2fsvtnpd3xtz6l47s":["mintzeppelin","Mint Zeppelin"],
"o2f3lqdfxn7cavzy6jtcqrts":["miraidon","Zephyr 🔞"],
"qsc5dpshr3u2mbn4j5y5ihkn":["monoccrow","Zeph/Sam @ Animaga 32"],
"jal22hb5fm7zi63f7casowyl":["mrzephaniam","MrZephaniam"],
"jdzqocv7qtx6yn3wdjxaixbl":["mrzeppo","MrZeppo"],
"tgaomd4qgf63eekmu54vdlgd":["mrzephyrus","Zephyrus "],
"6s3inenubzhn4b7cuycml74t":["mxzepix","Zepix 💚 (commissions closed)"],
"b65mbnhbjwb7ixfcbqms5kma":["my-zephyr","my_zephyr"],
"qvo4fbxnb3krolvce7gwy7nf":["neonzephyr","Neon Zephyr"],
"5n6luch3sddxms76ayl6f3yf":["noahpasternak","frank zeppo (noah)"],
"epylbiiz5vrbeo4iwta5fnme":["novakorpov","Bred Zeppelin "],
"r4nmwey4gzskfdh6uf7uqwgt":["ntzeppelin","ntZeppelin"],
"gj36yyfsl32rxizej6h6ahzn":["o0zephyr0o","Zephyr"],
"tx27esmv3fvgb2tzqefm23gf":["oceanicmoth","Zephaniah"],
"j6cgmlll563gzblcv2uc6na2":["paramixzeph","Zeph"],
"rmek5qcypm2uhiariinq3sv6":["particlearts","zeph"],
"xndifi25b4tg7efmazlefqp2":["paranormalzeph","SpoopyZeph"],
"eeu6aoxgr65xxpv2hqxzal3h":["princezephyr","Zephyros Nemesis"],
"whygl3c3aoimdb7rogo666qh":["princezephyr27","Prince Zephyr"],
"d5js5wc3pdmczzxk6kefiyfq":["zephyrwrestles","Zephyr (they/she) "],
"v4aepy66iyqzpdoftx5wxoaq":["razept","RaZept"],
"dpmnmbtstsp66h3fmd4zsopn":["reitzephyrox","Reit Zephyrox"],
"rpb4mudscgrx3mxtuptqpj6a":["rezept","Zephyr"],
"tnnzvtflz4b56e3dwmh5yp66":["reshiram","✩ Zephyr ✩"],
"n3rgerqzyaqsywmeo4c3yhd6":["reapthegirlwind","Zephyr"],
"txh3s2hlydsnkl43xlifb3i7":["realzephyrdark","🏳️‍⚧️Zephyr Dark VTuber🦅"],
"kmrv6avs4bsc6fr6dedc2o4e":["rewzi","Zephyr"],
"q3xnb37icze6efw5pljjxvkl":["redzeppelins","Red Zeppelins"],
"glubzkh7w5hspnwtxbjop45y":["rebelzephyr104","Rebel Zephyr"],
"5hiw27vnmetxjfpfy4jiqzvc":["rgzepeda","Raúl Zepeda Gil "],
"myw7c7lxgnvlwwdcojx6sl76":["rocketsgoto.space","Zeph"],
"azl3n6iydbk46rn2kan5u3u5":"rock2zep",
"2jovc6yd6cqid6xmw5cskemj":["robsonsilva","Zephtyr"],
"w6uez3sofwwlltvfzcyrdrmy":["rowdyowly","Zephery but sussy..."],
"wnrthefwxzyn5pfhabe4svmx":["rose.zephyr.pet","Rose"],
"lyzrafcdoebrg7vqelw5sgki":["rubberbutt","Zephyr"],
"3g3zaoxqd44jf3j536hpvmfk":["rystaxan","Zephaniah"],
"ruh5rhm5ymkaiqplyuw7wbek":["ryze522","Ryan Zepp"],
"wbnuqewrdilxjzvkhz4llojn":["saintzeph","Saint Zeph"],
"ju55iuykrmfiylahmvl5mfbc":["shadzicx","Zephyr / Midnight"],
"z6qaalwfoeej6f3pinh4f67o":["sjwfutch","Zephyr/Gulê"],
"wkka3gvhxm3gsbygqxndkoco":["sloppyheadwind","Zephyr After Dark 🔞"],
"uif4c2hnosa257udx63quenj":["smithghostology","Zephyr🌪️"],
"m4p4jkon435e3rbqmsjx6dli":["smochizeph","Zephryus Atreyus"],
"floruunmtcbhcgeqxp6thnrd":["sonorouszephyr","Zeph"],
"mb4fgc5a6i3wgvo2mfwr772u":["soulzephyr","It’s.a.zephyr"],
"r47ic3lhwoc7bh2t5xnd26t5":["sophithetanuki","Sophia Zephyr"],
"2gcc5odwfr6q466sxld2ntol":["spaceboizephyr","🌌Space Boi Zephyr🌌"],
"d4znj2etu3svzh2ur6ziieqy":["stardmytro","Led Zeppelin"],
"swgszhg5kk7ahf2rnuysru5d":["stardustzephyr","StardustZephyr"],
"nb5r64stwbxviu4apgphocrj":["stefanzeppenfeld","Stefan Zeppenfeld"],
"5jkctuhwkojzn74us3yvpsbs":["stormfly","zeph"],
"cmz6cvtdxqhph7i44xkuq5ur":["sublimezephyr","Zephy"],
"e65nocjeiowt7axzvj6e4leu":["tepizep","Zep Tepi"],
"damztutrhnqkoik5gjrs3iji":["theinnkeeper","Chad Zeppelin"],
"tx7lfngt2payfl7e27lg4bvj":["thestarryman","Zephyr "],
"cahlsbuspvfckfoom6llqiao":["themarszeppelin","TheMarsZeppelin"],
"nzwfk64q4aucug6lluwqmmcv":["theplantghoul","Zephyr"],
"b7ryao6blulbgu4nhhtiwkuq":["tk-zephyr","tk"],
"wqpg4qrxg5fey3v6mnbqejnt":["tootderg","Zephyr"],
"6niju3u3uhkzrgx7a2dwmg5b":["tristancaine","zephyr"],
"pg5orsk3k3xim567rsdpnol2":["twistedzepher","Zephy"],
"xi3z7cjvv37xwn4hre33mp4w":["unboundzephyr","Zephyr the Horny Dragoness"],
"dodasnc5jvbpceobvfjqf7uq":["vampsfilmology","Zephyr🌪️"],
"fngq23ajokb4jnw7qsnvfzsb":["vesper.zephyr.pet","Vespy ♡"],
"kmqfxtq6erttlajcm5a2mslo":["verzephx","Zephyr"],
"x2di2iqayo5wz5kaw7au3sdj":["voyagerstarbug","Zephyr"],
"3hpm2g4ou3ynzfsr6llyfll6":["waywardzephyr","Zephyr || Pirate Gaymer Extraordinaire"],
"wpk3dq7wlyf6u6p33j5atkdp":["whorenadowarning","Zephyr's Nested Folder 🔞"],
"xftv3gallsdb4k5im5vkfc7g":["windwaker1401","Zephyr/ Wind"],
"cmx5vzywavfgjc6sdcmwfsid":["wormbagged","Zep"],
"xp7tfmlrryuuy75pvsepaqpc":["woolenzephyr","Zephyr"],
"wgpyvr47xklmstwtvg6suvdc":["xoxlabs","Erik Zepka"],
"g22hvmwugjg5rnysgegmv5tq":["yubermis","Yubi of Zephyrion"],
"wsurpzbq5a5jullzrkupkgfm":["zcfleetwood","Zeph Fleetwood"],
"3kqv7i6swotbefi6xvsoytxb":["zepiter","Zé Pedro Silva"],
"4zqdojzqkukx4cv5iskvuowx":["zepheryowl","Zephery"],
"5cnvrldqyc2egxyijrvbxzri":"zephycat229",
"64754cqfle625ncer3h2awir":["zephlin","Zephlin"],
"6phclvbpd6aqqvvm7owk54f7":["zephyrsymax","Zephyr Symax ΘΔ 🔞"],
"7m5f4iioaffzukkd2gp7klix":["zephkit","Zephkit (Commissions OPEN)"],
"7tl6l2su5ehtzdc6ms5tllao":["zeppelin","최 제플린"],
"adl7dsevh3l6f3wbnkj4ltsx":["zephyrderg","ZephyrFloofyDerg🔜Furcation 2023"],
"ajgcipmdkdyg2jsjifk6xmbb":["zepicelli","ZePicelli"],
"bjcaziyusgsltrxe3hcmmx7k":["zeph06","Zeph B."],
"bknqzvxp4j5ytmh7ytltieiv":["zephyriwolf","Zephyri Wolf"],
"c2r4hhkw2gvu2ec7xraiq4kv":["zephry","Zephry"],
"dba5zcn4cukrci562xjirntz":["zepiou","Zepiou"],
"dkiisfr64gkka24vdoul7jmr":["zephyr-er","재필"],
"dmqjmyjkzleuahzigsofpwur":["zephamphar","Zeph ✨"],
"ekd6nc7alv5lp77thvjasrow":["zepaw","Zepaw"],
"hfzsy33kyumoo4sqrti3vgew":["zephyxus","Zephyxus (Zephy) 🦈🐺"],
"hurqbai6nqyv564dsrtapxo2":["zephzeuski","Zeph"],
"hyp3ukwmbn74xhdazh2e6k2q":["zephyrchill","Lord Rodin, Relocated Warrior"],
"idi2ezpex25huji7q6nl6hcu":["zephyrnok","Vance"],
"itro6efoizuuwdthcuctwjrq":["zephymeg","Meg “Nope Not a L3” Rickman"],
"j54ykfxlig6acmx6srmbktrv":["zeph163","Zeph"],
"jel4is54ku777hwsp76lenzo":["zephyrbug","Zeph🌾🕯️"],
"jqc4i4t774kpwc4dub7oxe4s":["zephsep","Zephyr 🌿🏳️‍⚧️"],
"l22elrvgia3j7vvoinmxizej":["zephyrlot","Zephyrlot"],
"lhfg4r2z3lfdtkty6bkqksfv":["zephles","Zephy"],
"lvliruj43lbdizwo2ti2ljl7":["zephyrsword","Zephyr~"],
"mlwbehfzqgf4dweo3rsnhdti":["zephyrmoth","cemetery trash mammal"],
"nio4rgvtn5afz5zv2dgnug7q":["zepp1968","Zepp1968 "],
"npjczna3gabwfip6e2euxdzr":["zepharusbirb","Zeph快鷹 🦅⚡️"],
"nus5tfvlcnewou6d34mkv7jp":["zephyrhaze","zeph"],
"ny3wtwqsnvua75fgdgk73va5":["zeparcher.com","Zep Archer"],
"ogvl5d5xgjtno3ig652ojkbk":["zephyrjackal","Zephyr Jackal "],
"ovi5mmsbxymtrifrgu7gytp2":["zephyrousfox","Zephyr"],
"ow7s5nur73uaiphv4fautrm7":["zephyrtiger","Puss in Crocs"],
"pe6eejbtlwncqc7aix54fxlf":["zephyrusorg","Zephyrus"],
"qfkghdz2ubmeuzuqre3odarx":["zephyderg","Zephyr"],
"rpqx2gyzqcwnkcdkyphz5rep":["zephonator","Zephonator"],
"sbdd3ytk7do6doysi2ih3s2c":["zepag","Pierre-Antoine Grégoire (zepag)"],
"tkcnopoehby63yvkyna5x2hf":["zeptentrion","zeptentrion"],
"u7iceuo4cneli6ttaqwibgnc":["zephra","Zephra @BLFC DD"],
"ufjgr6iopbeoezu2mw2dtwr7":["zephyrmang","Loving Dup|Zephyr Mang|DOE DONE W/ TOUR"],
"v7mfbuysroonbq3q74qpo5r6":["zephyry","us ghostal service 🏳️‍⚧️"],
"vbn6z3zbdkvr6iad6pgwhjal":["zephyrusbirb","Zephyrus™"],
"vconeygbh3o5qnbvt3bhbeuy":["zephonsacriel","Nicholas Perez"],
"vlxunjxigdsxdawpxfvs6nzy":["zephyrsky","🖤♡Amanda♡🖤"],
"vq45kvtpcrlffytykuxvxzvd":["zephosk","Zephosk"],
"xq7wtvbbhvi4cei63oy74fif":["zephls","✨️ Zeph ✨️"],
"xxtqio7eirz6gbnwptyv2hig":["zephyr13","Zephyr"],
"y2odkcunxq4zfgwt7aob7ae7":"zeppelinagain",
"4rppbcmyjnil5tcjg4yyqruy":"zeph",
"bxpsobk3zxqrir4qoslje7rh":["zephyr","tsubasasa"],
"athozkmjt2lpo3gfkwvz3kze":["zephoria","danah boyd "],
"ax7zchnmz6jikwr7sqxx53u5":"zephye",
"f5rzlnpzdejgty3j5wkpul2e":["zeppelinmagazine","Zeppelin Magazine "],
"ypngpgp4altbnbw3gbtma7js":["zephyrcalling","Zephyr"],
"gxgeseprraiw2lfrfai43q5v":"zepman",
"ftbakwcuqjcjgji2tkiiim6d":"zephsays",
"j6tukq3hfli2mczitotmqib6":["zepicteam","CEO of Cinder 🔥"],
"gkzrev2ajrptkxk6i4uzllbi":["zephrfish.choose.no.life.choose.no.career.choose.no.family.choose.a.fucking.big.messchoose.no.sleep.high.caffeine.and.mental.insurance.choose.no.friends.choose.combats.and.matching.trekking.shoes.chooselife.hack.porn","ZephrFish"],
"zze7un2dujfzuuy5n4sebjq6":"zepzard",
"hq6eu466pggynq3g6a2x5hb6":["zephiransas.com","Takafumi Yoshida"],
"mssyrit3nu5so2okvrnjm3y7":["zeprid","Zeprid💤"],
"ak4oc6ngsrj6iswgxbysvlcs":["zephr","Zeph"],
"kd5efmlzgxcrie2jayi6ip7t":["zepper7650","zepper7650"],
"chto6dasydeibi4eqfr6vxxn":["zeppeli","Isa🍔"],
"7aehdkvdyuladvta23h3wu2z":"zephyrstrife",
"76elqbpbpn4fh4emj3xnr5bj":["zephtheblue","Zeph the Blue Dogbot"],
"vfviydpkrlhdjwhngy5lfssv":["zepi07r","카페인맛☕제피/칼 "],
"j4h4ttj5z5y43s2nmtyzcgqv":["zephyrgales","Zephyr"],
"4qxyfgnfxcyp3kxezrcmrr52":"zeplinn",
"cv6zaie3aig4i3v3c6r4fn6t":["zephlei","Zephyr"],
"robhrwxyitcxvqrwsciyrbbc":["zeptor","Zeptor"],
"5xsal57rqv3l35dydh4lyivx":"zepy32",
"kum2fmqej6ml5epgxvmyuho3":["zeppelincomics","Zeppelin Comics"],
"asrsmxkhedmtrnz4unqckx3w":"zephyranth",
"cjtaftwmow3unx3x5nzthzzj":["zephaniah","Zephaniah"],
"ymnkzhcrrxymlpmmzcqxemcr":["zephyro7s","Zephyr"],
"wnt2owd23csrirdxwyzaompy":"zephyrith",
"idbv22ehr2vvlzkkrvyqqbdt":["zephygay","zephyr"],
"bpe5nk6ekugokrzs3q2z3cfp":["zeppole","Kate"],
"x3abqi3ufv2tyztxw3kx7u56":["zephyrin","Zephyrin☆*ﾟﾟ"],
"s76hc76ooym4phz2ugzea7te":["zepwae","great"],
"6qpno6mw26elzyj2hujx7vol":["zephyrthesmiler","ZephyrTheSmiler"],
"4usf2pehrvdw4nmlsju4p4js":"zephy",
"24pzicag5teezsscpho4pj3y":["zephdotpng","zeph 🔞"],
"worlz4blvti7atjx4cxiihcp":["zepirose","zepirose"],
"wz46xaks4ppapezxfgcy3z42":["zephyrhayato","Zephyr Vtuber"],
"gjbudoy2r3ibd4kzhiqz7vwj":["zepi","Matthias Zobrist"],
"jjlvfowdm4uiiwrim7y2dmqs":"zepsay",
"jdzqqx76ce3ek6r47qqxcpzx":["zephyrvescent","TIFF / THEO."],
"e2p32wyat72hm3z47qhbkpyw":["zepog","Z"],
"bqs5jb37ptg7ctlkn2p56jag":["zephcourtney","Zvph Cvvrtnvy"],
"mk5gaf4ghyywbcv42nu7lsvz":["zephyrus-wolf","Zephyr"],
"idwmtosygwndtcx23pgxqzt4":["zephyrembyr","zephyr"],
"rqftyxsxeub4v744gcchwiml":"zephyh",
"bi6yi7mnokurycjpb3qyeync":["zephemeral","Zephemeral"],
"bygpmpx7pokddcrgu4zqcwxw":["zephyrwolf","ZephyrDirewolf"],
"sgqamb6fszggglohagcw6txn":["zephyrarcturus","Zephyr"],
"u5ho2sjt7ai24jrnvspioks2":["zephyxfox","Zephyxfox"],
"wb36ud46op5dxfwebit27lqk":["zephrius","Zephyr"],
"lfwskyh4xdmqwk3kjbdzkjxi":"zephyrrosenberg",
"ttmpe4e35oxkeqkgr3oio5dj":["zeph.blue","Zephy"],
"2stuqzogskkwfqul3lbjjg3t":"zephnya",
"ocgen5uerh7pom7eitlhmafz":["zephyrfox","Zephyr"],
"txqs2yygniqb5casdpxuvbbh":["zepto","Zeptophidia"],
"n575dxbgaiqwy3vro6nxesrp":["zephyrus","Zephyrus"],
"3sxngn3mzbgngmpnepk6bkfp":["zephyrfalcon","Hans St. Clair (Taylor's Version)"],
"euavkec2scg6a6k35gtghpzu":["zepter","Paulo"],
"ylbjitki6ff5jryn66bhhohu":["zephwright","Joe"],
"hungw6fgztzmovxzc6wquuew":["zephyrmoon","💙 🌌 𝐙𝐞𝐩𝐡𝐲𝐫 𝐌𝐨𝐨𝐧 🌌 💙"],
"5mvhw7gdj7oep4l2lsokooru":["zephyrquinn","Brian Dane"],
"6kakxmx4pymlhqq4gr7oslwb":["zepje","Zepje"],
"ngp6uhu5vp63u6kh4lfr3ux7":["zepyaf.com","Pierre-Yves ANDRÉ "],
"2cogojludpkb57aiod7tlv3s":["zeppelinaw.ooo","Zeppy!"],
"uop5zoekb4xdvycbw5qpy3xc":["zephyrlotus","ZephyrLotus"],
"qdw7dp6tqy3y4mfkg7ool5sg":["zephyrium","Zephyrium"],
"wmauz3akoi4ei5veo3jsfo6u":["zephyrwusky","Zephyr"],
"edap5s2dz4d2r3spoggntftg":"zephyrpup",
"jmukcmkb6ttq5n2vgu2z27rz":["zephyrdrake","ZEPHYR"],
"i22iyozq4fnpgn4tvf3ubkm4":["zephiie","Zephiie"],
"k4wb2oa5jhwtmych5bh5eve6":["zephyrsplume","Your daily source of cat blep"],
"csbe7oadm4iv3pg2q7umfusu":["zephyrthedrake","Zephyr ΘΔ 🔞 "],
"rvsabjiu54hjaljlwfcwxb4s":"zephkr",
"7lq7h6lzilyeoqfvm6gzaomi":["zephyrrrx","Zephyr "],
"h7p2logjgdsn365bzkvwexk5":["zephil","Toby Horak"],
"s364tkbzcfaezygfqnivqhif":["zephyrwynd","Zephyr"],
"itgwr5bcrvx4xy3gemjhrpvg":"zephyrdawn",
"j6v7t5f5j7oiw6puifxx5za4":["zephyrpak","Zephyr.pak"],
"f5dn5uol6runuapkp76swvo6":"zeppeledlin",
"m5io6gcwieitqtwersrf4hkx":"zephyrum",
"surbsciixdkp5bi4af3eephj":"zephyrau",
"2v6xeumr4v2kyk2dr3vgnfne":["zephyrauster","Zephyr"],
"ro2trmb2szgsobn6yql37brc":["zepedac","Kristen was my dad’s name"],
"m33kfvs25k6pj3cl3da5fcih":["zephyrprotocol","Zephyr"],
"dy34ekqmjgjckrwzqul4l4fv":["zephyrstarchild","🎃👻💜Zephyr Starchild 💜👻🎃"],
"qc35jsm5oy4o7ssg2tw2flkq":["zephlerrr","zephlerrr"],
"wcfgq2sfer5zkmpeuzeirdsx":["zephuko","zeph"],
"vpssxfq4hfftw7hb4aqn3sgl":["zephyrnick","Nick W"],
"miqylenepuezwc6hzgituoqj":"zephyrcoderat",
"jmvddxogswyusemxu4jcljac":["zeph0r","☾★ 𝔷𝔢𝔭𝔥𝔶𝔯𝔦𝔫𝔢 ★☽"],
"kjcdj3xm5vggk7i2ajdqgttn":["zephyranthes","zee!"],
"drweze3sqesvxo4hvjvlmm4g":["zepeda","Zepeda"],
"e67qf5kzli75yslarmr7tqrm":["zephyrusgryphon","Zephyrus"],
"7ljj6hl3coq4vtckogpqqr73":["zeplander","ZepLander"],
"si5otqgerbayd2wmjocmtbdx":["zephyrworkshop","AEGIS Combining Robots is Here Now"],
"ll7yuu536leyar4abrjg75xn":["zephiriel","Zephiriel"],
"xdp4ofnlxadsvsr2nllk3r4s":"zephkr7",
"tveqt5mvrsrmqxwxg33i25tl":["zephyrtheotter","Zephyr"],
"rplsw67zv2zix3u3rfqnjzci":["zephyrholmes","Zéphyr Homes"],
"6qznkidaaoxekjabe57iwlur":"zephyrine",
"ievazbzxorgrr4fk47us5szw":"zep",
"36ycgc32fdcuurkq7jw2mzmm":"zepatate",
"26eahwhhb5vybnsusevt7kqs":["zeppi","Zeppi"],
"fhvxvby6dzr37hhzuugpdjbb":["zephyr47","Zephyr"],
"syqjbpllhskhyxveq5r4kskt":["zephsbeans","🍖Zephyr Yeen🍖 🔜FurPoc"],
"pzy7h3gmgxecqsc4rhl5mdut":["zephyrtora","ZephyrTora"],
"dkpy5vtepikbsqvj22eh76ik":"zepe",
"ijvmznzx4o7udjez4bh5kohd":["zephrotting","Zeph_Rotting"],
"jhrtkzkrt2kkfe6t4nvbtbbu":"zepol",
"sz3c7o7kvglgabirmg4qmz4o":["zephyr0713","Zephyr"],
"kuzqz2655woot7ofz67zgnhg":["zephyrcheez","Zephyr"],
"vea5y34ttjt4ycl546xbj4xy":["zephyrfrost","Zephyr Frost"],
"g3ht6pqnswgmvot3kb3arvqf":["zephyrhu","Weiser Péter "],
"j6tamjdmrtiuedh3tysfymqj":"zepherix",
"fwifpwhm4epbbhvginko5zwc":["zephwuff","Zephyr"],
"apnuysolia5w34y5eualx3yb":["zephyrj","Jay"],
"d3f4hcbu4ox6qvujdculpuyh":["zephyrflowers","Zephyr Flowers"],
"4fxsxcfxcroxagbrairsnq2c":["zeporto","Phoenix"],
"35zf6wsa44x2xvecej4lfua3":["zephyrosel","Zhire"],
"bm2q3ivdq4wsgud7tjweu7su":["zephyrusfs","Zephyrus"],
"nby3qvsouzrte4umvhj5hmld":"zephyr442",
"ackkcpl3urn4exl3dubhl5nb":["zephisleepy","ZephiSleepy"],
"hmcqbkusvjnpx3iq6yxkeauc":["zephoros","🦯Zephyr🦯"],
"dqjiobsessu3beoj6k7cv64o":["zephyrhusky","Zephyr Husky"],
"wthuooyb2244num6g5e3svkv":"zepsipepsi3",
"aldzt3ofgocibfxawg36elu6":["zephir","Zephir"],
"dinqlkd72w3ixnsj7ri3c5rx":["zepzep","Zeppy"],
"jndruimpqkcbpzmqfdwfjzhx":["zephilline","Chris Frazer"],
"jvdng5zzc6ilgo7ibbddajtf":["zephyrrdragon","Zephyrr"],
"ax525kmuz43wgi7ylkrodzsi":["zephindle","дед бомж"],
"dnfqebso6azy6mtfembvycxs":["zep109","zep109"],
"ecjppi7mw2lrrn4zlfnf3rcu":["zephyrflash","Zephyr Flash"],
"2fujx6pee3jv4i5doxdxucr3":["zephyrfog","Zephyr Fog (FFXIV)"],
"qdzabo57bzn7vntbfomemeys":["zephyromir","✦ ZEPHY ✦"],
"v5srko6e4e37sjevtlykx3c2":"zephyrdawn8",
"lmzet6ldl25bewwpvsjywiqh":["zephyrskunk","Zephyr Skunk"],
"kf2lcghmzmvqtqrlkaf46mn4":"zephyyeen3",
"3rgzwvty66ngdsoywct4kpz4":["zeppy64","Zeppy64 🌌 Space Dad VTuber"],
"oov6lnfbql5nmyfh42tmyndk":["zephyrnoodler","Zephyr"],
"cq3mzplajpj6qxp664ptvsjg":"zepsipepsi0",
"drklolr3ubpxgawvx5qdxhk3":["zephyrfolf","Zephyr Folf~"],
"36reqnb72i3lppb3jm3fxz2r":"zephyra",
"csgnikymqrg2ihjdi4qlna25":["zephyrferret","ZephyrFerret"],
"3f4hew5xiz3xe3mqyz7mqmyd":["zephyroh","zephyroh 🐀👑"],
"m7c2oadu4ezkwmecwcmidfet":"zephyrusk",
"k2m5bho5c45km4uocpxhpqas":"zephyriine",
"bkqm76tygu2wx6aiqwgiff62":["zephyrstar","Belly Enthusiast"],
"7sd7ohaihjtxxmsumxqmy6fg":["zephyrwoof","Zephyr!"],
"j7xguzmiyobf7hnruojg74kx":["zephthefox","🏳️‍🌈 Zeph The Fox! 🦊 | Pup Ty 🐶"],
"kzcdljza357qt7k4l7xyf35n":["zephsahl","Zeph"],
"47k5on4d4bs6zga45hx4gasz":["zephys","Zephys"],
"ydkqjfcwp5xjijzjpqupsqgk":["zephy03","ゼフィ"],
"3applyei7icyb2w5ycdhr2an":["zephmakesstuff","Zephy"],
"fxs3gstg3ud7ei3t463abcur":["zepplin76","Zepplin76"],
"mmhisnpucvobfsl5vidahl5d":["zephyrventus","Solara Zenith ☀️"],
"myzysqaar2q52lymzhe7gl5p":"zepadovani",
"qwwsli3l22fv7juhvon5uith":["zephyrix","Zephyrix"],
"j3py2oponemcv5c332s7vhku":["zepandovski","Zepandovski"],
"v6tn43p7ttksv6hh5uyn6dbe":"zephkr5",
"365p4h7rk4bgble6g7wjq54s":["zephyrstormwind","Zephyr"],
"gxzhjqslk5u2nktcibwssct2":["zephyroust","zephyroust"],
"pjciq373bywv26or3tcfgc5s":["zephet","Zephet"],
"rbycmcalwjkd3iftuts7pu5a":["zephrily","Zephrily❀"],
"f7u2d5rf4xm354qyw5wl2xxd":["zeplenx","ZeplenX"],
"jfomgidztfnddcblmclgcudm":["zephyrkushala","Zephyr the Kushala Daora"],
"hjdj6uasrfmyfsa5cfxov46z":"zephyrplushie",
"ntdqbhkziw4azceyhbty3qwx":["zepyhrbytes","ZephyrBytes"],
"yd62adn3xhrdyscfhlrwe7rl":["zephyrwolfeh","Zephyr Wolfeh"],
"h33cvfq4vtbgh45inknib5zo":["zephleph","Zeph"],
"tvjlzro7xa3wmb6zd5momcgb":["zephynyx","✨ Mystical Ink Zephy ✨"],
"qlcd2ivt4faltvendlkt3t7p":["zephyretiger","Zephyre Tiger"],
"imn4ra2m2l2cdhthx2ztssx5":["zephis","Zephis"],
"itkqy6qgayb2ka5fkbcrs7pt":["zepharen","Zepharen"],
"xhu5ntxzeicimy5bm7w3re5i":["zephleit","Zephleit / Ross"],
"64kk3tu3nzjdxwhgcivva6ux":["zephyrrose","Zephyr Rose, the lil pink pup "],
"luhcjwpvfarouiq5vxw4bv7c":"zepwich",
"q3ivjlwawfyaeqdpgncobqzh":"zeppomarxist",
"uudh3bprlrbzot6lyihr77e3":["zephyrr","Zephyr "],
"lvsm4vsuvtvhmdkwcf3bcnxo":["zephpaws","Caspian"],
"v2i4jsfz4yhjh3n5gkzinw7h":["zephyrp","Zephyr Peling"],
"rz4nsbz4al24a625jpkifwc3":["zephyrartz","ZephyrArtz"],
"ud4mceops5y5jvgmbuhbsgvo":["zephyrr29","Zeph"],
"bmpfs2zgf53c5vgtl4y2tieh":"zephenthegreat9",
"gkakg3yytglbgdzhf4v3uc2p":["zephamore","Zeph Amore"],
"opo4kr4qr5u74qzz6asagjkh":["zephyzx","Zephy"],
"oqsw7e4is4srk6wc5duvbomi":"zephyrdawn13",
"bzz6ogqr3yp4zs7gbrzcvmim":["zephoriax","Zephoriax the Skeleton"],
"fkhjmizsue6la6iekqyk4sr7":["zephyrflora","Kadi"],
"4gktdpxmxleljsmyu4l2zf5d":["zephirin","Zéphirin Zéfirelli"],
"fa32d5ekb5malv3ad7syzzzs":["zephyrrcue","Rif | Zephyrrcue"],
"ssl2resksajzqdxdc6fwsq34":"zephyr023",
"wikzsqaoa67x4elr2siaosj7":["zepherl","Zeph"],
"v3b5c76pmxozsq4wmlwap3xb":["zephie","Zephie_AF 🏳️‍⚧️"],
"ku2ekooywe3buxehvq2ggvse":["zephyrrz","kafkafuura (ZephyrRz)"],
"7vn6fymha4kpnobypj67z6hl":["zephyrlucha04","𝖹𝖾𝗉𝗁𝗒𝗋/Pugsley"],
"j2mqdqz7gafelu7j7wj5mfsr":["zephyr-ergane","Zephyr"],
"zb72tn3kbj7rhxf5qeu7n5eq":["zephyrmakesthings","✨️ Zephyr ✨️"],
"4yptxwp535xxbd3dnqata6iv":["zephyrblayze","ZephyrBlayze"],
"rfn6dtvn27agxkgsyyjjkkxp":["zephfav","Zephyr Favonous "],
"x3gqcgjwu5ebxmg7i24ltdgh":["zephyroth","Fred_Is_Dev"],
"lng7zt77pgdrkfenrclqtoj6":["zeptepe","zeptepe"],
"ts4zmalw2k4mel2hwpa2uzue":"zephyrion",
"cyhw3bdudks47qypd5whoiva":["zephofgale","Zeph"],
"feevniolwfevjuv2q36wrz5w":["zephyrfoxart","Zephyr Fox"],
"3c3tpmjigy7bcyvb2sc7qwbv":"zepzepzep",
"ygekmml3wdyyhx73q62lavxs":["zephyrsolo","Registered Flex Offender"],
"2mofcdjhv7hxq3vj7svlwcob":"zephenthegreat5",
"tgsrm3aqza4iu3gvvf4zwwkb":["zephiro","Zephiro"],
"2jsybwq5muxw52f74qcaoac6":["zephy092","Zephy"],
"grx355ht62rvnqw5ijmz7h5k":["zephyraart","🎃🦋Spooky🦋🎃"],
"7p6b2zso2p4d275zfg7i55mp":["zephercatnap","Zepher Catnap"],
"3ma2q5ag7f5gnchriej5b7yl":["zephyrs","Zephyrs"],
"74tvdfntvipf7xhva2ywedvr":["zepho","Zepho the Swolebot"],
"kfrqoh6727qk5svw2swlxgvm":"zepoke",
"xkoazsejayfnbb7uxmryobjf":["zephraxe","Zephraxe"],
"c63jsx5ay555hzzhvmdmicpt":["zephyrtwink","Pup Zephyr"],
"q2mvopxukebhvbqaozhr5cu4":["zephyskunk","zephyr"],
"q3edncincu2jbzpwaxk77em6":["zephrado","Zephrado"],
"vlj7cv2gamwdhdlmk75vzmpc":["zepyromancers","Ze Pyromancers!"],
"fysyrh6o7cdvjyy7lngy27r4":"zephyr04",
"dqaaz2ldeyvu6bc4aw525gww":["zepheri","Zepheri"],
"qhgz4cz5dvbvz2l3ghlotbcn":["zephrus","Althalos"],
"5kfyfn5fzhygbglmujjqahrn":["zephyrzilver","ZephyrZilver"],
"xvknde44dxyuo7ldxgpmpdk4":["zep1le","Larson"],
"fqolssaig7nbfkph6kdvgzgg":["zephkr24","zephkr"],
"xngcc3uiwkihdu2lt5mphiks":["zephur","Zephur~ 忍者"],
"vcjan3x6khtlmyxfeo4kuxyh":["zepiereite","Zepi!"],
"a4aaym6h7yj3myk2aaz66lgf":"zephyr31",
"6wmuqq4yaaewyy2qsjcrayfu":"zephyrmoor",
"o2ei2u7sgkzstekwa3ntzklm":"zephyrdawn4",
"eevq2qlb2dks32v7hiewynox":"zephyrabyss",
"uvyd2rofyj3dzdtq2gwdl7qa":["zephyraeros","Zephyr"],
"db2dyudjwkbvoyvt5qpzoglb":"zephyr-the-sergal",
"qqbhzh5wtvrd7q2u6h6smdzf":["zephhareng","Zeph' "],
"srcqudhnqadaqqvpy23alguv":["zephyrphil","Phil"],
"ucz63d7x5c6xfinrn6bqlcrp":"zephiyn",
"5cs3esl7ee7fcbshtjqtagry":["zephyraphim","Miggu"],
"owmotftrfdkkmudadn76jndg":"zeppypeaarl",
"amm3ryhkqtycq3airgie5q26":"zepiwolf",
"57trg5i3j3cvqiqvndri2dvo":["zephry6","Zep"],
"gfwq2uaam7zydwcomxu2dj3q":"zephero",
"q3llmhuubitarl64wjhpcoww":["zephram","Zephram"],
"4nhqgwsn3ql3zcu3pnkha5lb":["zephucks","Zeph the Gryph 🔞"],
"qm37ce2vrsurt7fu63wtxmzf":"zephjdj",
"thkj3mterq5d3yvanyxtauxa":"zephyrkaze",
"i3bgeb5s2fj6yk7sy7tb6jus":["zephronart","✨🎃Zephron the Spooky Wizard 🎃✨"],
"spyguh3zp5sj33s4xlbjjtqd":["zepharasite","Zeph"],
"zyi6iybtd5catb465f7cdint":["zephyrkid","ZephyrKid"],
"sp5lkikdb24bvs6ijtfww27v":["zeplinates","Zeplin Ateş"],
"vyrchhlkqgpkrprw4bmb34y4":["zephyrusyx","🔞💜Zeph💜COMMS OPEN✨Multifandom✨"],
"7gyjnydowpyxauwkhpxrcz6h":["zeppiecv","Lewd Lizzie"],
"fmkhkypmzoehmmrso2veltz3":["zephyrdoesarts","💀 ZephyrDoesArts 🎃"],
"qtbcljxk6o6inshpevbzkjmf":["zepp","Zephaniah"],
"bxkjhuy66ddsdcaemycfr5if":"zephyrdawn21",
"w3khg7b4nb4xchcgktz55ruf":"zephyros",
"cmareagra5wwvkwvinavsg3a":"zepg",
"ngc5xc4esearxwpodmzlmlob":["zeppersart","Elijah"],
"m3afrb3mqjqeeoanam4znabu":"zephormite",
"bw4l73u6zekb2o5c5puauyxj":["zephryna","Zephryna Trinity"],
"iuacq75ouwh2xqyx7ful444a":"zepla",
"clwhnbtl6kfbjmba67ttf76l":"zephen",
"u4ntkkuezcf5tfvxkapaa26v":["zephyrusxevach","Zephyrus_Xevach"],
"5gf5j2noyaxtlc5qea2c5drm":["zephvee","Zephvee"],
"rfzvdww6us5wuvnabqtmfhro":["zephyr2984","Zephyr"],
"lfyauycokdfbzodbvfrsq2l4":["zepouet","ZePouet@Massilia"],
"4kymo4bvxflshsxshlc4pb4a":"zephem",
"ywys6yvtkmvngi7ogaxc2c35":"zephkr19",
"el7z64kf3iww52ycjzbw6vyh":["zephyreds","zali !!"],
"ugxf5bekjk2u2btiuj37ecqx":["zephyrmetalwing","zephyr 📿"],
"6e4jm5whtnampv6p4grprdnn":"zephyrchaotix",
"zlekdtm7jzb6fxgjcb2kfshp":["zepar","zepar"],
"h5j2t4x7kiu6wrzk3trvj5cw":["zepenguin","Denis"],
"rxkse5ih42h7txoicnq4nqal":["zephyrwolfy","Zephyr"],
"gch2elig3wx7v5mq7k4o4zk7":["zephirick","El Gabo"],
"dopyp4ejn5acpwrxhv7i5gi6":["zephyrr3d","Zephyr Red"],
"w6dt4h47i3yuymhztmsfksyz":"zephy4113",
"anucovnds5y7onkx65vfpggq":["zephinlivingston","Zephin Livingston"],
"d5ydtjcqbu6xaxquxnzlxdry":"zephraxis",
"vujx36ykiz3jh7hopj3s5tcx":["zephyr2802","Zephyr_2802"],
"fohbgpp6fdhkwyzcaoepqfqi":["zephyrial","Zephyr"],
"ytqoggtpfif3oncetylz6nz5":["zepostman","Jean Bardin"],
"xgmd6qdssp23q2wqzposlloa":["zephyrrcat","Zephyr"],
"m6s3golwvvfkwm6jtekatxon":["zepherys","Zepherys"],
"f6sdio274hrfrfsc7ob7ff6g":["zephyrz","zephyr"],
"t6y3croch57fiburezcumuoh":["zepekenho","zepekenho"],
"7ur2huvetjq4sad2dqiwygmj":["zephyrienne","zephie"],
"pvz3nyqsucgkg62lca5bcmzi":["zephyr256k","Zephyr256k"],
"uvuvcusvkqchpkawofk3thmh":["zephfair","zephfair"],
"mfz4vedy6s6dd5olkhphq6p4":["zephyrusad","Zephys Dungeon "],
"6dxeuqhfs23filn3o2jatwtq":["zephyrwrex","Zephyr Wrex"],
"mrqzfdqckon5fwj3xmnds2z5":["zeusacraeus","Zeph"],
"ftevxflhr6cl2jx6goghrijz":["zephiirre","Zephiirre"],
"lmwojm76cnqpnrija2khbtel":["zephyrosthelazy","Zephyros"],
"dbedpmb6db7fsbqcasqxlcum":["zephyrlodicieux","Zéphyr l’odicieux"],
"u5sevognxyafcbilzhw3e4k3":["zephfr","Zeph"],
"f2ihi7p37yffuci5cvkavkek":["zephirinetae","Cherry🍒"],
"tbb6aembx2pzgmr5jtfzrih5":"zephuscursed",
"5ocw4igwbcvyxya7jeam4chm":["zephunknown","ZephUnknown"],
"7pnlwmicqos465phqszatnpc":["zephytheleopard","Zephy"],
"fln5zppozky64h6jd5chgqz5":["zephirock","Zeph "],
"gpwvb327g52323e4cdao4lca":["zephyrnoodle","Zephyr The Noodle"],
"n66t3k3lfp6f7a2xmppzl5i5":["zephanixiv","Zephani :."],
"naz3twfszwmzspgyiafolcd5":["zephfurious","Zephfurious"],
"tl7u5ip7xyj7nvz2lx2hkv35":["zephsk","Joseph Boinay"],
"qibyrl3za3lacegk3d6h3o7x":["zeppo","Zeppoos"],
"uwnimmpadzdfri7zrsmqnlp3":["zephyralchemy","Alchemist Zephyr"],
"qov3v4whk5kd5lpmgpbmpxbd":["zephyrspirit","Zephyr "],
"hpkdxpqg7gqelykxvxmzukwu":"zepnik",
"pw6n3h2jefth4drygaitj4p7":"zephyrxf",
"ngi3buepnshgmaehzgttf5cd":["zeptotf","ZeptoTF"],
"wlipa43olj747vpej2p7cfrh":"zephyrtiger1",
"orsncxygvhi6g7mgfiqj73oz":"zep3lino",
"5lfa7mckg5h4h62xhslpf2zi":["zepuwi","Zeitpunkwichtel "],
"2ujej4ncmijexknfngxlrioz":["zephyrzoya","Zoya"],
"ahdtomaem7gtpsofdo7r56xv":["zepoulp","Zepoulp"],
"aiusisqnwvdpyk6tgsou5coe":["zephyrastralos","Zeph"],
"3kbnj7e26llbfqrsadepejqt":["zephyrthegoat","🐐 Zephyr 🐐"],
"pwchtqiso4muhncju32dp4xg":["zephyrsurge","ven"],
"2zybqareywkqcln6lpeeoqbl":"zephyyeen23",
"viimoanngg34tgfjownex6wz":["zepulus","Zep"],
"ymwt2ps26attbdvihf5tmiy7":["zeppy","zep"],
"si63amyy3faqspqwx6j5hbz5":["zeph-phyr","zeph "],
"uao3nkrzv4jqpueoasuom2tx":["zepppizza","Zepp Pizza"],
"mrmlbwnikv7udvk3cluuacju":["zephyriates","Zephyr"],
"fdmgjg6panxsg6s3rx35af73":["zeppelig","G."],
"5nzeb5tm2xe6slf7sj42vpuk":["zephyrrh","Zéphyr"],
"sveavui3xdh2u4jaetfy7vph":"zephyr096",
"lhprlnozmdufwn5umr23ak47":["zephri","Roy"],
"xslwvrnkdb3svlpti4bklxly":["zephyfoxy","ZephyFoxyArt"],
"he2u5slt4f2o56v36im4r2rl":"zephyreean",
"r37ex73pjxabffrz6bv6hl7w":["zepony","Ze_pony"],
"an2ih2yu7r23p5sxiakwnls2":["zepartst3r","William"],
"oqv6d5udwrk33vbzdrovcuda":"zephyrstarz",
"qqmaemythg3p6ajtssgj6ixp":"zephrampoke",
"uzcfosougwi7mrkgakkrjjjd":"zephyrwagon",
"ss6x4i3ggpfqgq7cyufkbmah":["zephgg","Austin | Zeph"],
"4ddztxstlekgzjxy5qnfadrf":["zephyyeen","Zephy"],
"qdc7uxmhvhihak2ib5gmhs4k":["zephyr-the-otter","Zephyr"],
"ofq2c55vew5zcg32pe32wy7t":"zepheird",
"67qjzhbxjc7ufapoc2yb7ec4":["zeppe899","Zep"],
"shr2ooziqsctrsnbetc5wzyr":["zephyx-is-blue","jones"],
"hzyskge66hsncxofp2plfcbu":["zephyrb","Zephyr B"],
"arkewhfpmr52tac32p2spy4a":["zephyr1906","Zephyr"],
"opy4qzbses6ckt3ms543pdm3":["zephyrdragon","Zephyr"],
"wxqblkbmkfpoyskrkbni4pem":["zeppelinlg","Zeppelinlg"],
"j5yxn4ltifcyzyfgx26ktne2":["zeph310","Nick"],
"fto6rwevb2rhhrtyuh3igcbv":["zephyr616","Zephyr (18+)"],
"ccpaxwreoda5vegqqd5hrllh":["zepolmot","Zepolmot"],
"tts4dubx7w66e34fvzjm6nqk":["zephx","Zeph"],
"q5xobwxob3f6ivxosx65lrsf":"zephyrinjackalope",
"nybc3qqvydf5e2v7wtzhudzz":["zeraph","Zeraph(inda) Zephyrial"],
"rkkydpssodkz7f6gnv7vvuw6":["zephysonas","Zephysonas (Composer/Mixer)"],
"owujctjuwutulal75h3kwov5":["zephyrcub84","Zephyr"],
"7w5gpihflgaf4bl2cjz6anlz":["zephyrowur","Zephyr"],
"j53ldlxnveqcj7wqvfkz3szs":["zepouille","chouette effraie"],
"wayo7uc3vuk63eurzboiud2d":["zeperion","Nergigante"],
"akejg46tiw7fidh6hrgza3ya":["zepheris","Zepheris"],
"56ztxgkmaq73dhkzavumha34":"zephiasero",
"sbtt6vkyuk444dtfghq6snnn":["zepolenta","Gabriel Naldis"],
"tb3bnp47n73ry4du7jmz5jqh":"zepol98",
"6zjen5vh7b75xytorvq6nulh":["zephyrskies","ZephyrSkies (Artist)"],
"fvxfucsfxh5jf4s64nigrkub":["zephyrias","Zephyr"],
"okmpeasuz3nrwwzmmzvramta":["zephyrsilver","Zephyr_Silver"],
"j4tv2od3fg3hnf6uefuaxqws":["zepy","Zepy"],
"mjwy2zqe6vyw4evzwvztwdlu":["zephirin-v","ゆーすい"],
"2ioyz6ge4c7n3dbyz4vkxh5x":["zeptember","Steph, ztepf (They/Them)"],
"tjkjkfj4zpueazgcoqeovksy":"zephyrcider",
"z4ficl5lr4ncpctubv6b7jh5":["zephyrcyrax","Cy"],
"z7kcdglwtjpkazmgm5kltztx":["zephyruspup","Zephyrus"],
"2timo2k3emu7kekcrl65xay4":["zephyrin56","Bernard.Dessy "],
"bdpo2gwrmlwyyqmaxamr7d7z":["zepa","aku"],
"wc42wa6yxzryo3upp3srluuc":["zepirate","ZePirate"],
"f3uje56vb34qjgwc63c6co3o":["zephyrical","Zephyrium"],
"g3ws33eiycnlra755iq4uhsn":["zept","Zept"],
"lxbbaxrinkxqvwirwfw2vgea":"zephyris",
"jdrbvbtfp7mtsjhmjhz35x4v":"zephyruseek",
"lcprhfzckjfeap7k2mea7e7o":["zoandbehold","Rep. Zooey Zephyr"],
"cefpysbtnm2bngfj4l74sw63":["zphyf","Zephyrus Fusky"],
"y6jbi6o3ymegoharjjigjjsq":["zthefiend","Zeph 🏳️‍🌈"],
"5ngx5xqrrbblkoebp4fjci6z":["z-zeppo","The Zeppo"],
"zsahvk32bf3uplebad2c2k2p":["paynannr","zephyr "]
}
