{
"sa7odqnkilv6kdyrb2jh2tzj":["izhylenko","Ihor Zhylenko"],
"i72efsd56potjpyzsesvye7m":["liveinzhytomyr","Zhytomyr Man"],
"3gbhbbyzqdh23xhfveksdufs":["nikitazhytnyk","Nikita Zhytnyk"],
"ok2uzoqgzsymywifsvaowewl":["valeriizhyla","Valerii Zhyla"],
"cxz775d2nmxb2oe2hdtxr4oj":"vlad0zhyrov",
"q25yrbqkxwrnilrjvrwdbk4f":["zhtnk.me","Oleksii Zhytnyk 🇺🇦"],
"vnot5t4mzob3h22tliyyr5k4":["zhya","雑兵A"],
"yhxmzozbd27xcy6zyvbeecxs":["zhyvchykamb","Lisa"],
"pjbdjnxqovkjwyq6syqauf52":["zhyhir","Сашко"],
"ocj7ef2iqawq5igze7sqcekm":"zhyu",
"llwmf6gv4w5lf2xqbttvebai":"zhyn",
"xhbemhurxdp4l47momdtnj5c":["zhye","jack"],
"clis22kkwhyqlavxj7bgg23d":["zhyrafa","Zhyrafa 🌸"],
"sk3f5fv4uvrnks7qlrdloobp":"zhytyiradity",
"rn5sbvyrfxnx5wkerhy4xzxx":["zhylo","Zhylo"],
"anuytnw4aj43wxppne2cn3ma":["zhyun","즈현"],
"w7imopdh6dji7cnckwdz5ydd":["zhylko","Жилкос"],
"ttghct6b2tuokzx7usxgx4tm":["zhygou","Tierra ZhyGou"],
"cousgrqet5b66to254uye7vi":"zhyrux",
"3gcvfufnpdq3rjmlscjw7jhw":"zhyruk",
"5ixjtyau6orfio3pigzlutxx":["zhynka","Люда Дєнісава"],
"g5voqrfbrprb7bstw7dtlawl":["zhyv0n","zhyv0n"],
"oykf6opzdi3ngec7l5mu2xsp":["zhymon","Simon"],
"tdvxi23eigdtfrnvgfzzsiek":["zhyrnyipes","Zhyrnyi Pes"]
}
